setup.py
PyLogDecorate/__init__.py
PyLogDecorate/log.py
PyLogDecorate/logtest.py
PyLogDecorate.egg-info/PKG-INFO
PyLogDecorate.egg-info/SOURCES.txt
PyLogDecorate.egg-info/dependency_links.txt
PyLogDecorate.egg-info/top_level.txt