Metadata-Version: 1.0
Name: PyLogDecorate
Version: 0.33.4
Summary: Advanced python logging decorators.
Home-page: https://github.com/offlinehacker/PyLogDecorate
Author: Jaka Hudoklin
Author-email: jakahudoklin@gmail.com
License: BSD
Keywords: python logging decorators
Platform: UNKNOWN
Classifier: Development Status :: 4 - Beta
Classifier: Topic :: Software Development :: Libraries :: Python Modules
Classifier: License :: OSI Approved :: BSD License
